skan/__init__.py
skan/_testdata.py
skan/_version.py
skan/csr.py
skan/draw.py
skan/image_stats.py
skan/io.py
skan/napari.yaml
skan/napari_skan.py
skan/nputil.py
skan/pipe.py
skan/pre.py
skan/summary_utils.py
skan/test/__init__.py
skan/test/test_csr.py
skan/test/test_draw.py
skan/test/test_io.py
skan/test/test_napari_plugin.py
skan/test/test_pipe.py
skan/test/test_pre.py
skan/test/test_prune.py
skan/test/test_skeleton_class.py
skan/test/test_summary_utils.py
skan/test/data/retic.tif
skan/test/data/skeleton.tif
skan-0.12.3.dist-info/licenses/LICENSE
skan-0.12.3.dist-info/METADATA
skan-0.12.3.dist-info/WHEEL
skan-0.12.3.dist-info/entry_points.txt
skan-0.12.3.dist-info/top_level.txt
skan-0.12.3.dist-info/RECORD
